heart_library/__init__.py
heart_library/attacks/__init__.py
heart_library/attacks/attack.py
heart_library/attacks/evasion/__init__.py
heart_library/attacks/evasion/hop_skip_jump.py
heart_library/attacks/evasion/laser_attack.py
heart_library/attacks/evasion/query_efficient_bb_attack.py
heart_library/catalogue/__init__.py
heart_library/catalogue/manager/__init__.py
heart_library/catalogue/manager/manager.py
heart_library/catalogue/manager/mlflow/__init__.py
heart_library/catalogue/manager/mlflow/client.py
heart_library/catalogue/test_catalogue.ipynb
heart_library/catalogue/workflows/__init__.py
heart_library/catalogue/workflows/create/__init__.py
heart_library/catalogue/workflows/create/object_detection_patch.py
heart_library/catalogue/workflows/evaluate/__init__.py
heart_library/catalogue/workflows/evaluate/patch.py
heart_library/catalogue/workflows/optimize/__init__.py
heart_library/catalogue/workflows/optimize/patch.py
heart_library/catalogue/workflows/search/__init__.py
heart_library/catalogue/workflows/search/patch.py
heart_library/catalogue/workflows/workflow.py
heart_library/config.py
heart_library/estimators/__init__.py
heart_library/estimators/classification/__init__.py
heart_library/estimators/classification/certification/__init__.py
heart_library/estimators/classification/certification/derandomized_smoothing.py
heart_library/estimators/classification/pytorch.py
heart_library/estimators/classification/query_efficient_bb.py
heart_library/estimators/object_detection/__init__.py
heart_library/estimators/object_detection/pytorch.py
heart_library/metrics/__init__.py
heart_library/metrics/metrics.py
heart_library/py.typed
heart_library/utils.py
heart_library/workflows/__init__.py
heart_library/workflows/harden.py
heart_library-0.7.0.dist-info/LICENSE.txt
heart_library-0.7.0.dist-info/METADATA
heart_library-0.7.0.dist-info/WHEEL
heart_library-0.7.0.dist-info/RECORD
